async_scheduler/__init__.py
async_scheduler/exceptions.py
async_scheduler/job.py
async_scheduler/scheduler.py
async_scheduler/utils.py
light_async_scheduler-0.0.2.dist-info/LICENSE
light_async_scheduler-0.0.2.dist-info/METADATA
light_async_scheduler-0.0.2.dist-info/WHEEL
light_async_scheduler-0.0.2.dist-info/top_level.txt
light_async_scheduler-0.0.2.dist-info/RECORD
