Metadata-Version: 2.1
Name: light-async-scheduler
Version: 0.0.2
Summary: A function based scheduler based on the async event loop.
Home-page: UNKNOWN
Author: Ellis Lunnon
Author-email: ellislunnon@gmail.com
License: MIT
Platform: UNKNOWN
